functional_cache/__init__.py
functional_cache/test_functionalcache.py
FunctionalCache-0.1.dist-info/LICENSE
FunctionalCache-0.1.dist-info/METADATA
FunctionalCache-0.1.dist-info/WHEEL
FunctionalCache-0.1.dist-info/top_level.txt
FunctionalCache-0.1.dist-info/RECORD
