Metadata-Version: 2.1
Name: FunctionalCache
Version: 0.1
Summary: SQLite function cache
Home-page: https://github.com/thomas9911/FunctionalCache
Author: thomas9911
Author-email: thomastimmer11@hotmail.com
License: UNKNOWN
Platform: UNKNOWN
Classifier: Programming Language :: Python :: 3
Classifier: Development Status :: 4 - Beta
Classifier: License :: Public Domain
Classifier: Operating System :: OS Independent
Classifier: Intended Audience :: Developers
Classifier: Topic :: Utilities
